regolith_json_template/__init__.py
regolith_json_template/py.typed
regolith_json_template-1.3.2.dist-info/LICENSE
regolith_json_template-1.3.2.dist-info/METADATA
regolith_json_template-1.3.2.dist-info/WHEEL
regolith_json_template-1.3.2.dist-info/top_level.txt
regolith_json_template-1.3.2.dist-info/RECORD
