Metadata-Version: 2.1
Name: regolith-json-template
Version: 1.3.2
Summary: A Python package for easier reuseability of the JSON Template Regolith filter for Minecraft Bedrock Edition
Author: Nusiq
License: MIT
Project-URL: Source, https://github.com/Nusiq/regolith-json-template/tree/master
Classifier: Development Status :: 5 - Production/Stable
Classifier: License :: OSI Approved :: MIT License
Classifier: Programming Language :: Python :: 3.10
Requires-Python: >=3.10
License-File: LICENSE
